{
  "sha": "03c53b25ea36c3007291192105f956819fd0543afa848f75d8f8c7d2c7571d48",
  "provider": "groq",
  "model": "meta-llama/llama-4-scout-17b-16e-instruct",
  "yaml_bytes": 1244,
  "description": "Create a GitHub Actions workflow named Build and Deploy to Azure that triggers on push to the main branch. Use an ubuntu-latest job to check out the repository, set up .NET 9 SDK, restore dependencies, build and test the project, publish it to a local directory, zip the output, and deploy it to an Azure Web App using zipDeploy with a publish profile from secrets.",
  "tags": [
    "dotnet",
    "azure",
    "webapp",
    "deploy",
    "zipdeploy"
  ]
}