{
  "sha": "0b85108bae0d14acce955a3d523878aae4ca3db6e41edc261e7d1655f0537046",
  "provider": "groq",
  "model": "meta-llama/llama-4-scout-17b-16e-instruct",
  "yaml_bytes": 597,
  "description": "Create a GitHub Actions workflow named Push Container to Heroku that triggers on push to the main branch. Use an ubuntu-latest job to check out the code, log in to the Heroku Container registry, build and push the container to the djangosnippets app, and then release it.",
  "tags": [
    "heroku",
    "container",
    "push",
    "release",
    "github-actions"
  ]
}