{
  "sha": "19852da8af6a7794eb77fe71a10d7006ca93ecff7fd7921094d4d1b7f5357c5d",
  "provider": "groq",
  "model": "meta-llama/llama-4-scout-17b-16e-instruct",
  "yaml_bytes": 830,
  "description": "Create a GitHub Actions workflow named Stale that runs daily. Use a single ubuntu-latest job that utilizes the actions/stale@v3 action to mark issues and PRs as stale after a specified period of inactivity, and close or delete them if no action is taken.",
  "tags": [
    "stale",
    "issues",
    "prs",
    "automation",
    "ubuntu"
  ]
}