{
  "sha": "19b63d6013762ba6a840dab69451d2c5407199f42e3dd036905f177006e380db",
  "provider": "groq",
  "model": "meta-llama/llama-4-scout-17b-16e-instruct",
  "yaml_bytes": 1797,
  "description": "Create a GitHub Actions workflow named Tests that runs on push and pull request events. Use a matrix strategy to test across multiple Python versions and operating systems, with a timeout of 20 minutes. For each job, check out the code, set up Python, upgrade pip, cache pip dependencies, install project dependencies with make setup-ci, run tests with tox, and optionally upload a coverage report to Coveralls.",
  "tags": [
    "python",
    "tests",
    "matrix",
    "tox",
    "coverage",
    "ci"
  ]
}