{
  "sha": "1bc334021982b051181bcd9ab5bc6bfe80a43fb54fbbcc6ad2010def045a4b0d",
  "provider": "groq",
  "model": "meta-llama/llama-4-scout-17b-16e-instruct",
  "yaml_bytes": 3069,
  "description": "Create a GitHub Actions workflow for building RPM packages on openSUSE Leap. The workflow triggers on push, pull request, and release events, ignoring changes to README.md, LICENSE, and BUILD.md. It checks the commit message for a disable flag, then builds and packages the project for openSUSE Leap 15 and latest using a matrix strategy with different build types.",
  "tags": [
    "opensuse",
    "rpm",
    "cpack",
    "linux",
    "cmake",
    "qt"
  ]
}