{
  "sha": "1e63f6e39656bbcfce1f87a9e9fcd049825dfd6de0eefc6a21f8852bece0302c",
  "provider": "groq",
  "model": "meta-llama/llama-4-scout-17b-16e-instruct",
  "yaml_bytes": 3300,
  "description": "Create a GitHub Actions workflow named Arch Linux that runs on push and pull request events. Use an ubuntu-latest job with a matrix strategy to build the project with both GCC and Clang compilers. For each build, run a Docker container with the archlinux:latest image, install dependencies, and execute build and deploy scripts. Distinguish between release and daily builds based on the Git reference.",
  "tags": [
    "arch-linux",
    "docker",
    "gcc",
    "clang",
    "continuous-integration"
  ]
}