{
  "sha": "21ebf585994667352534087e12446c42b16a41240edea2a557328cda7af7da85",
  "provider": "groq",
  "model": "meta-llama/llama-4-scout-17b-16e-instruct",
  "yaml_bytes": 1288,
  "description": "Create a reusable GitHub Actions workflow named CodeQL that performs code analysis. The workflow should run on an ubuntu-latest environment with a matrix strategy for C and Python languages. It should check out the repository, initialize CodeQL tools, attempt to autobuild compiled languages, and then perform CodeQL analysis.",
  "tags": [
    "codeql",
    "security",
    "analysis",
    "github",
    "reusable-workflow"
  ]
}