{
  "sha": "223c164fce31dce8df5b4386116d6dd0b478eaeb3e642db5c1cec501d736ed5a",
  "provider": "groq",
  "model": "meta-llama/llama-4-scout-17b-16e-instruct",
  "yaml_bytes": 3100,
  "description": "Create a GitHub Actions workflow for basic CI on push events, excluding markdown files, with concurrency control to cancel in-progress runs. Run the workflow on Windows, Linux, and macOS environments with various configurations, including setting up the environment, installing dependencies, building, and testing the project.",
  "tags": [
    "ci",
    "windows",
    "linux",
    "macos",
    "cmake",
    "conan",
    "multijob"
  ]
}