{
  "sha": "22adb720f8b56a2216190b591b3b163f0994ca0cfdd06675aa901ac1d466880b",
  "provider": "groq",
  "model": "meta-llama/llama-4-scout-17b-16e-instruct",
  "yaml_bytes": 485,
  "description": "Create a GitHub Actions workflow named param check that triggers on push to specific files: src/overlay_params.h, README.md, and data/MangoHud.conf. Run a single ubuntu-latest job that checks out the code, sets up Python 3.11.2, and executes a Python script named params.py located in the tests directory.",
  "tags": [
    "python",
    "params-check",
    "github-actions"
  ]
}