{
  "sha": "22bc242408d9514fd74788f0a44cfb9c97bedaad550a88b30f13694d8857d50c",
  "provider": "groq",
  "model": "meta-llama/llama-4-scout-17b-16e-instruct",
  "yaml_bytes": 205,
  "description": "Create a GitHub Actions workflow named nrf52840_dk that triggers on push and pull request events to the master branch. Use a job that inherits from a build template located at .github/workflows/build_template.yml, passing nrf52840_dk as an argument.",
  "tags": [
    "template",
    "workflow-reuse",
    "nrf52840_dk"
  ]
}