{
  "sha": "2606510050bd6071e8ff63ff55ab45601b077e7a55e076d3d94c62c88e6aa83c",
  "provider": "groq",
  "model": "meta-llama/llama-4-scout-17b-16e-instruct",
  "yaml_bytes": 1275,
  "description": "Create a GitHub Actions workflow named github-Linux-32bit that runs on push and pull request events. Use a single ubuntu-latest job in a container, checking out the code, installing multilib support, configuring Kokkos with specific CMake flags for 32-bit builds, building the project in parallel, and running tests with output on failure.",
  "tags": [
    "linux",
    "32bit",
    "kokkos",
    "cmake",
    "tests",
    "ubuntu"
  ]
}