{
  "sha": "2baa14089046b4083207b3aed89f7914e9bfcbbb5a1c374e50c716b5f4a181b9",
  "provider": "groq",
  "model": "meta-llama/llama-4-scout-17b-16e-instruct",
  "yaml_bytes": 256,
  "description": "Create a GitHub Actions workflow named MyCi_MacOS that runs on every push. Use a single macos-latest job that checks out the repository, installs Qt using the install-qt-action, and then runs a Qt project by building it with cmake and make.",
  "tags": [
    "macos",
    "qt",
    "cmake",
    "ci"
  ]
}