{
  "sha": "2bec5ae9bd675a499a681a030d22019687cd9afc90466432760d12918b7c8ca9",
  "provider": "groq",
  "model": "meta-llama/llama-4-scout-17b-16e-instruct",
  "yaml_bytes": 15234,
  "description": "Create a daily GitHub Actions workflow named Daily Tests that runs every day at 7AM UTC and allows manual triggering. The workflow consists of multiple jobs: generating a build name, building gem5 with various configurations and images, running unittests, and executing long tests with different types and configurations.",
  "tags": [
    "gem5",
    "daily-tests",
    "github-actions",
    "ubuntu",
    "linux",
    "self-hosted",
    "long-tests",
    "unittests"
  ]
}