{
  "sha": "2c5efc91628c7398db97951116a9992b1cac0b2e4d55b5a5d8a9885f8814dcbe",
  "provider": "groq",
  "model": "meta-llama/llama-4-scout-17b-16e-instruct",
  "yaml_bytes": 2023,
  "description": "Create a GitHub Actions workflow named CodeQL that analyzes code on every push to the master branch, on pull requests to the master branch, and on a scheduled basis every Friday at 15:00. Run a single ubuntu-latest job with a matrix strategy to analyze C++ code using CodeQL. Checkout the repository, initialize CodeQL tools, build the project with cmake, and perform CodeQL analysis.",
  "tags": [
    "codeql",
    "cpp",
    "ubuntu",
    "cmake",
    "scheduled",
    "analysis"
  ]
}