{
  "sha": "335b1348ca91ece2035cd169950d715496a1b98074c10527b04203e389a74a34",
  "provider": "groq",
  "model": "meta-llama/llama-4-scout-17b-16e-instruct",
  "yaml_bytes": 2172,
  "description": "Create a GitHub Actions workflow named Coverage that runs on push and pull request events. Use an ubuntu-16.04 job to check out the source, install vcpkg dependencies, generate the German locale, install ninja and coveralls, configure CMake with vcpkg, build, test, and upload code coverage to Coveralls if the repository is jupp0r/prometheus-cpp.",
  "tags": [
    "cmake",
    "vcpkg",
    "coveralls",
    "ubuntu",
    "code-coverage",
    "tests"
  ]
}