{
  "sha": "344466d3d9d63669fc349af9ebaaa40d68bf608d67ff1b9604059ba4d4498557",
  "provider": "groq",
  "model": "meta-llama/llama-4-scout-17b-16e-instruct",
  "yaml_bytes": 13616,
  "description": "Create a GitHub Actions workflow named CI that runs on every push to the develop branch, on pull requests to develop, on a weekly schedule, and on workflow dispatch. The workflow has a build job that runs on ubuntu-latest and macos-latest, and installs dependencies, ROOT, Geant4, and optional dependencies. It then configures and builds Gate, and runs CTest.",
  "tags": [
    "ci",
    "gate",
    "geant4",
    "root",
    "ubuntu",
    "macos",
    "ctest"
  ]
}