{
  "sha": "355929fc5060c24501f2d7f3b9d1e7c5018371127528828c740a30ead5ba1a67",
  "provider": "groq",
  "model": "meta-llama/llama-4-scout-17b-16e-instruct",
  "yaml_bytes": 505,
  "description": "Create a GitHub Actions workflow named fuzzer that runs on every push to the master branch and on pull requests to master. Use a single ubuntu-latest job with specific environment variables, check out the repository, install dependencies, prepare the CI environment, and then run tests using scripts.",
  "tags": [
    "fuzzer",
    "ubuntu",
    "ci",
    "tests",
    "linux"
  ]
}