{
  "sha": "42e00b40c2b4718bfd62af975670c10d01e2b15730955906de3e704ccc623528",
  "provider": "groq",
  "model": "meta-llama/llama-4-scout-17b-16e-instruct",
  "yaml_bytes": 2028,
  "description": "Create a GitHub Actions workflow named docs that builds and deploys documentation. The workflow can be triggered manually, on push to main, development, or development-2.0 branches, or on pull requests targeting those branches. Use an ubuntu-latest job to check out the code, set up Python 3.10, install dependencies, build the docs with make, and deploy them to gh-pages branch, only when pushing to main or development branches.",
  "tags": [
    "python",
    "docs",
    "github-pages",
    "deployment",
    "make"
  ]
}