{
  "sha": "484b26eb3780d7855ed8c93d288d8b3fddc0d170f470067a943bff8f320f634e",
  "provider": "groq",
  "model": "meta-llama/llama-4-scout-17b-16e-instruct",
  "yaml_bytes": 988,
  "description": "Create a GitHub Actions workflow named lib build that runs on push to master branch, tags matching v*.*.*, and specific paths, as well as on pull requests to master. The workflow should have two jobs, x64 and x86, both running on windows-latest. Each job checks out the code, sets up the MSVC development environment for the respective architecture, caches libraries, and then sets up the libraries using a batch script.",
  "tags": [
    "windows",
    "msvc",
    "cache",
    "libs",
    "build"
  ]
}