{
  "sha": "48be389226b8e3c82fd0bc98abf3ae5c77d12ac1c935a095c86f785d2a4db88f",
  "provider": "groq",
  "model": "meta-llama/llama-4-scout-17b-16e-instruct",
  "yaml_bytes": 3569,
  "description": "Create a GitHub Actions workflow named Create Release that triggers on push events with tags matching 'v*'. The workflow should create a release with source distribution and development tools archives. It extracts the tag name, sets filenames, creates a source distribution by archiving the repository and submodules, gets the tag message, creates a release with a detailed body, and uploads the source distribution and development tools as assets.",
  "tags": [
    "release",
    "github-actions",
    "tag",
    "archive",
    "automation"
  ]
}