{
  "sha": "4db58cbd2d6d1afb2711312639b0534e6f6e6996a28285bd7a9d28f8b64c04fb",
  "provider": "groq",
  "model": "meta-llama/llama-4-scout-17b-16e-instruct",
  "yaml_bytes": 14313,
  "description": "Create a GitHub Actions workflow for building Doxygen on multiple platforms. Trigger on push and pull request events. Use a matrix strategy to run a build job on various configurations including Ubuntu with GCC and Clang, macOS with Intel and Apple Silicon, and Windows with MSVC. For each job, check out the repository, use a custom build action with CMake, and upload build artifacts.",
  "tags": [
    "doxygen",
    "multi-platform",
    "github-actions",
    "cmake",
    "ubuntu",
    "macos",
    "windows"
  ]
}