{
  "sha": "4df319ac536d868e5703fc27623ed65f189b4fabfa2f0b299ce3c3ffb1aeeec1",
  "provider": "groq",
  "model": "meta-llama/llama-4-scout-17b-16e-instruct",
  "yaml_bytes": 1022,
  "description": "Create a GitHub Actions workflow named Docker devcontainer image that triggers on push to the master branch when the Dockerfile in docker-images/devcontainer is updated, or on a workflow dispatch. Build and push a Docker image with a specified tag to Docker Hub using credentials from secrets.",
  "tags": [
    "docker",
    "devcontainer",
    "dockerhub",
    "workflow-dispatch"
  ]
}