{
  "sha": "58584dee65086c2f14396a100225610084551006af09cfe7ad72eb32a6b9392d",
  "provider": "groq",
  "model": "meta-llama/llama-4-scout-17b-16e-instruct",
  "yaml_bytes": 5942,
  "description": "Create a GitHub Actions workflow named CI-Windows that runs on every push to the master branch and on pull requests to master. The workflow also allows for manual dispatch. It uses a Windows 2019 environment to build a project in multiple configurations with different Qt versions and architectures. The workflow checks out the repository, initializes submodules, caches Qt, installs Qt, configures and builds the project, packages it, and uploads artifacts.",
  "tags": [
    "windows",
    "qt",
    "ci",
    "build",
    "github-actions"
  ]
}