{
  "sha": "651c22f13e74fde046fe3851147f7be07d2f9b794a698cc2b40c35ea3e63d54f",
  "provider": "groq",
  "model": "meta-llama/llama-4-scout-17b-16e-instruct",
  "yaml_bytes": 5298,
  "description": "Create a GitHub Actions workflow named CentOS System CI that runs daily at 3 am and on pull requests to the master branch. Use an ubuntu-latest job in a centos:7 container, installing git, setting up the environment, and running system tests for BioDynaMo.",
  "tags": [
    "centos",
    "biodynamo",
    "system-tests",
    "ubuntu",
    "schedule",
    "pull-requests"
  ]
}