{
  "sha": "74f3bb7898c01f98c5f95b28d4d1de1d6c9c255c38f0b875c3d391ee5f7b7dee",
  "provider": "groq",
  "model": "meta-llama/llama-4-scout-17b-16e-instruct",
  "yaml_bytes": 4141,
  "description": "Create a GitHub Actions workflow named Autorelease that runs on push to the master branch. The workflow should set up a Windows environment with WSL, install dependencies, checkout a repository, build and package the project for Windows and macOS, and release the builds with tags and assets.",
  "tags": [
    "autorelease",
    "wsl",
    "windows",
    "macos",
    "github-actions",
    "release-workflow"
  ]
}