{
  "sha": "76e4a7c8017b4602e8e9fcb7a11ee2369e0b2632813e46dfcd941e36f1fffa45",
  "provider": "groq",
  "model": "meta-llama/llama-4-scout-17b-16e-instruct",
  "yaml_bytes": 1020,
  "description": "Create a GitHub Actions workflow named VS16-CI that runs on push and pull request events. Use a windows-latest job with a matrix strategy for Visual Studio 16 2019 on Win32 and x64 architectures. Check out the repository, then use CMake to configure, build, and install the project, and run tests.",
  "tags": [
    "windows",
    "cmake",
    "visual-studio",
    "ci",
    "tests"
  ]
}