{
  "sha": "8864d6f6c89b6ccbffb896db96a908ec66a3890ba0ac9f472a8245cb40461ecc",
  "provider": "groq",
  "model": "meta-llama/llama-4-scout-17b-16e-instruct",
  "yaml_bytes": 734,
  "description": "Create a GitHub Actions workflow named CI that runs on every push and pull request. Use two ubuntu-20.04 jobs, one for linting using psf/black@stable and another for building and publishing a Python package to PyPI. The build job checks out the code, sets up Python 3.7, installs dependencies, builds the package, and publishes it to PyPI if the event is a push with a tag.",
  "tags": [
    "python",
    "pypi",
    "ci",
    "ubuntu",
    "linting",
    "build",
    "publish"
  ]
}