{
  "sha": "8d5ce7e05b3fb0e3adc7d470c0d7029722c4728c087aa3442208915006350238",
  "provider": "groq",
  "model": "meta-llama/llama-4-scout-17b-16e-instruct",
  "yaml_bytes": 338,
  "description": "Create a GitHub Actions workflow named New workflow that runs on every push. Use an ubuntu-latest job for static analysis, checking out the repository, running static analysis from a local action, and checking the CHANGELOG.md file with a diff-check action.",
  "tags": [
    "static-analysis",
    "ubuntu",
    "changelog",
    "github-actions"
  ]
}