{
  "sha": "8e1b592514f8caeb3e90d85484d7f7cb6ee3196b42439df33908f11c5cafe2e5",
  "provider": "groq",
  "model": "meta-llama/llama-4-scout-17b-16e-instruct",
  "yaml_bytes": 2978,
  "description": "Create a Linux CI GitHub Actions workflow that runs on push to main and on pull requests. Use an ubuntu-latest job in a container with a specified image and environment variables. Checkout the repository, cancel previous runs, fetch submodules, build and test the project with make, package the results, run tests with xvfb-run, and deploy to AppCenter on push events.",
  "tags": [
    "linux",
    "ci",
    "ubuntu",
    "container",
    "make",
    "appcenter",
    "tests"
  ]
}