{
  "sha": "965ec2a68f805aac5e67147a48eff9025339a14b7be8f259792ed692ec8eba9b",
  "provider": "groq",
  "model": "meta-llama/llama-4-scout-17b-16e-instruct",
  "yaml_bytes": 1522,
  "description": "Create a GitHub Actions workflow named validate-p4c that runs on every push to main and on pull requests to main. The workflow should validate P4C compilation of P4-16 programs in parallel with normal tests. It should use an ubuntu-latest job with a recursive checkout, ccache, and a Docker-based build and validation process.",
  "tags": [
    "validation",
    "p4c",
    "docker",
    "ubuntu",
    "tests"
  ]
}