{
  "sha": "a13a8c32720a0c92a18cc22feb8b5733a35b6c14c7ebb6c2eee323b46d8d29a8",
  "provider": "groq",
  "model": "meta-llama/llama-4-scout-17b-16e-instruct",
  "yaml_bytes": 639,
  "description": "Create a GitHub Actions workflow named Publish packages to PyPI that triggers on push events with specific tags. Run a single ubuntu-latest job that checks out the repository, sets up Python 3.x, installs build dependencies, creates packages using python -m build, and uploads them to PyPI using a GitHub action with a provided PyPI password.",
  "tags": [
    "python",
    "pypi",
    "release",
    "tags",
    "github-action"
  ]
}