{
  "sha": "a5577a658762e51071c02a08db19b34328d648c17b25f970836bfd681bd94d0e",
  "provider": "groq",
  "model": "meta-llama/llama-4-scout-17b-16e-instruct",
  "yaml_bytes": 497,
  "description": "Create a GitHub Actions workflow named uno_binary_size that can be triggered manually, on push to the master branch, or on pull requests to master. The workflow uses a reusable build template for binary size analysis with specific settings for the uno board, checking against size limits, and an additional job with extra arguments to disable forced inlining.",
  "tags": [
    "binary-size",
    "github-actions",
    "reusable-workflow",
    "uno",
    "fastled"
  ]
}