{
  "sha": "abd359af07401a9d8110f90b46f7396a6f2c5933878386e0ea41f862968ec862",
  "provider": "groq",
  "model": "meta-llama/llama-4-scout-17b-16e-instruct",
  "yaml_bytes": 3719,
  "description": "Create a GitHub Actions workflow named Crowdin Action that triggers on push to the crowdin-trigger branch. Use an ubuntu-latest job to synchronize translations with Crowdin by checking out the repository, then using the Crowdin GitHub Action to upload and download translations with specific settings, and make a pull request with translations.",
  "tags": [
    "crowdin",
    "translations",
    "github-actions",
    "i18n",
    "l10n"
  ]
}