{
  "sha": "b30599d8abecad21635546576c857a81651b6a53b764b55236fb8b7983015e60",
  "provider": "groq",
  "model": "meta-llama/llama-4-scout-17b-16e-instruct",
  "yaml_bytes": 1463,
  "description": "Create a GitHub Actions workflow named Test that runs on push to the main branch and on opened, synchronized, or reopened pull requests. Use a matrix job on ubuntu-latest to test multiple Python and Django versions, checking out the code, setting up Python, caching pip dependencies, installing dependencies with pip, running Tox tests with varying Django versions, and uploading coverage to Codecov.",
  "tags": [
    "python",
    "django",
    "tox",
    "tests",
    "codecov",
    "matrix"
  ]
}