{
  "sha": "b4e7eae493f1d1b2cf06baccdcc05600804d9945992452ab950ca872d6fbfff9",
  "provider": "groq",
  "model": "meta-llama/llama-4-scout-17b-16e-instruct",
  "yaml_bytes": 558,
  "description": "Create a GitHub Actions workflow named sw that triggers on push and pull request events. Use a matrix strategy to run a build job on windows-latest, ubuntu-latest, and macOS-latest environments. For each job, check out the repository, run the egorpugin/sw-action, and then install flex and bison using the OS package manager. Finally, run the build command with ./sw -static build.",
  "tags": [
    "multi-os",
    "matrix",
    "build",
    "flex",
    "bison"
  ]
}