{
  "sha": "bb47666574ab790b2bba8e707dbae2778d440754d30a3ed7ae2b6ec92732a87f",
  "provider": "groq",
  "model": "meta-llama/llama-4-scout-17b-16e-instruct",
  "yaml_bytes": 336,
  "description": "Create a GitHub Actions workflow named C/C++ CI that runs on every push to the master branch and on pull requests to master. Use a single ubuntu-latest job that checks out the repository, installs gcc-arm-none-eabi, and then runs make in the wip-c++ directory.",
  "tags": [
    "c",
    "cpp",
    "make",
    "ubuntu",
    "arm",
    "ci"
  ]
}