{
  "sha": "c60adafa2c0f7a70c70ab1efc15d99f399ae6e2fdb73ef2f4783ec05c4726bd9",
  "provider": "groq",
  "model": "meta-llama/llama-4-scout-17b-16e-instruct",
  "yaml_bytes": 1337,
  "description": "Create a GitHub Actions workflow named Test that runs on every push to and pull request against the main branch. First, check if changes need to be tested based on the diff. If changes are detected, run tests in a matrix of environments with different C++ compilers, including g++, clang++-8, and clang++-10, and their corresponding C compilers. For each environment, build a test Docker image and run tests and style checks.",
  "tags": [
    "github-actions",
    "testing",
    "docker",
    "c++",
    "compilers",
    "style-checks"
  ]
}