{
  "sha": "c6adf094cd57f7f82a42e366bae6456165775fd359ab8908834fb6a732dbcf7a",
  "provider": "groq",
  "model": "meta-llama/llama-4-scout-17b-16e-instruct",
  "yaml_bytes": 1845,
  "description": "Create a GitHub Actions workflow named linux-ci that runs on push to the master branch and on pull requests to master. Use an ubuntu-latest job that checks out the repository, installs dependencies with apt-get and pip3, builds with meson, runs tests, generates and deploys documentation on push to master, and generates a coverage report with codecov.",
  "tags": [
    "linux",
    "ci",
    "meson",
    "ubuntu",
    "coverage",
    "docs",
    "python"
  ]
}