{
  "sha": "c7f5faced06bbb9920d22ebf088208236163cbdc94dd836d69288f53ba9e3fb7",
  "provider": "groq",
  "model": "meta-llama/llama-4-scout-17b-16e-instruct",
  "yaml_bytes": 553,
  "description": "Create a GitHub Actions workflow named CI that runs on push to master and hotfix/clang-9 branches, and on pull requests to master. Use a matrix job that runs on ubuntu-18.04 and ubuntu-20.04, checks out the repository, sets up cmake, compiles the code, runs tests, and saves the test artifact.",
  "tags": [
    "cmake",
    "make",
    "tests",
    "ubuntu",
    "ci",
    "artifacts"
  ]
}