{
  "sha": "cb2a5f697b1a2e460a8f60778b11cfeb5df24ab1e515645f7c956fbf38c09c02",
  "provider": "groq",
  "model": "meta-llama/llama-4-scout-17b-16e-instruct",
  "yaml_bytes": 7307,
  "description": "Create a GitHub Actions workflow named Windows Build that runs on push and pull request events for the master and release branches. The workflow should perform a Windows 64-bit build using a Windows 2019 environment, downloading and installing GStreamer, InfoZip, OpenSSL, and Qt, then compiling and packaging the OpenKJ project, signing executables, and uploading the installer to Google Cloud Storage.",
  "tags": [
    "windows",
    "gstreamer",
    "qt",
    "installer",
    "gcloud"
  ]
}