{
  "sha": "d836ff9247f5c9db7209f54a76340dc18c028a6b0a2d36848d46f0a2e2495cfa",
  "provider": "groq",
  "model": "meta-llama/llama-4-scout-17b-16e-instruct",
  "yaml_bytes": 669,
  "description": "Create a reusable GitHub Actions workflow named Python Build & Test that calls another workflow for linting and runs a Python application test job. The test job runs on ubuntu-latest, checks out the repository, sets up Python 3.9, upgrades pip, installs pytest and dependencies from requirements.txt if available, installs the package as a library, and runs tests with pytest.",
  "tags": [
    "python",
    "tests",
    "pytest",
    "reusable-workflow",
    "ubuntu"
  ]
}