{
  "sha": "d8e1c3d9da47897040d0e38f30860206a197fd1e13db2574e1021fdb4b7d324e",
  "provider": "groq",
  "model": "meta-llama/llama-4-scout-17b-16e-instruct",
  "yaml_bytes": 1258,
  "description": "Create a GitHub Actions workflow named External Repo: Tutorial: HelloWorld that builds and runs unit tests for the fprime-tutorial-hello-world repository. The workflow triggers on push to devel and release branches and on pull requests to those branches, excluding certain paths. It uses two reusable workflows: one to get the target branch and another to build the project, with the option to run unit tests disabled for the HelloWorld project.",
  "tags": [
    "github-actions",
    "reusable-workflows",
    "fprime",
    "tutorial",
    "hello-world"
  ]
}