{
  "sha": "f2fd27605c566b94326c8e91c2a70b833aa18ab655b03a3f56d5aab8c378fa66",
  "provider": "groq",
  "model": "meta-llama/llama-4-scout-17b-16e-instruct",
  "yaml_bytes": 1406,
  "description": "Create a GitHub Actions workflow named Check supported Compilers that runs on workflow dispatch. Use two jobs, gcc-build and clang-build, each running on ubuntu-24.04 with a matrix strategy for different compiler platforms. For each platform, check out the repository code and build the project using a Docker image with the specified base image.",
  "tags": [
    "docker",
    "compilers",
    "gcc",
    "clang",
    "ubuntu",
    "workflow-dispatch"
  ]
}