{
  "sha": "f4d3b36181c1242fb22fb21f891467d70100ff62a2356e8fd9f06b50e1b7f6fd",
  "provider": "groq",
  "model": "meta-llama/llama-4-scout-17b-16e-instruct",
  "yaml_bytes": 995,
  "description": "Create a GitHub Actions workflow named Release that triggers on release creation. Use a job matrix to run on ubuntu-18.04, checking out the repository, installing dependencies, building the project with custom CMake defines, and uploading the resulting packages as release assets.",
  "tags": [
    "release",
    "github-actions",
    "cmake",
    "ubuntu",
    "packaging"
  ]
}