{
  "sha": "f75102cd2613b918483b4c29304ecbf7ae162a1fcb803898042092325a8d92a7",
  "provider": "groq",
  "model": "meta-llama/llama-4-scout-17b-16e-instruct",
  "yaml_bytes": 1576,
  "description": "Create a CodeQL GitHub Actions workflow that analyzes code on push to the master branch, on pull requests to the master branch, and on a weekly schedule. Run an ubuntu-latest job with read permissions for actions and contents and write permission for security events. Use a matrix strategy to analyze Python and C++ code with CodeQL, checking out the repository, initializing CodeQL, manually building the project with specific configuration, and then performing CodeQL analysis.",
  "tags": [
    "codeql",
    "security",
    "analysis",
    "ubuntu",
    "cpp",
    "python"
  ]
}